odoo/addons/cms_account_form/CHANGES.rst
odoo/addons/cms_account_form/README.rst
odoo/addons/cms_account_form/__init__.py
odoo/addons/cms_account_form/__manifest__.py
odoo/addons/cms_account_form/controllers/__init__.py
odoo/addons/cms_account_form/controllers/account.py
odoo/addons/cms_account_form/i18n/cms_account_form.pot
odoo/addons/cms_account_form/i18n/da.po
odoo/addons/cms_account_form/images/cms_account_form_preview.png
odoo/addons/cms_account_form/models/__init__.py
odoo/addons/cms_account_form/models/account_form.py
odoo/addons/cms_account_form/templates/email_warning.xml
odoo/addons/cms_account_form/tests/__init__.py
odoo/addons/cms_account_form/tests/fake_models.py
odoo/addons/cms_account_form/tests/test_account_form.py
odoo/addons/cms_account_form/tests/test_controller.py
odoo11_addon_cms_account_form-11.0.1.0.3.dist-info/METADATA
odoo11_addon_cms_account_form-11.0.1.0.3.dist-info/RECORD
odoo11_addon_cms_account_form-11.0.1.0.3.dist-info/WHEEL
odoo11_addon_cms_account_form-11.0.1.0.3.dist-info/top_level.txt
